wumb_to_sqlite/__init__.py
wumb_to_sqlite/cli.py
wumb_to_sqlite/scrape.py
wumb_to_sqlite-0.1.dist-info/LICENSE
wumb_to_sqlite-0.1.dist-info/METADATA
wumb_to_sqlite-0.1.dist-info/WHEEL
wumb_to_sqlite-0.1.dist-info/entry_points.txt
wumb_to_sqlite-0.1.dist-info/top_level.txt
wumb_to_sqlite-0.1.dist-info/RECORD
