Metadata-Version: 2.1
Name: wumb-to-sqlite
Version: 0.1
Summary: Scrape WUMB playlists to SQLite
Home-page: https://github.com/eyeseast/wumb-to-sqlite
Author: Chris Amico
License: Apache License, Version 2.0
Project-URL: Issues, https://github.com/eyeseast/wumb-to-sqlite/issues
Project-URL: CI, https://github.com/eyeseast/wumb-to-sqlite/actions
Project-URL: Changelog, https://github.com/eyeseast/wumb-to-sqlite/releases
Platform: UNKNOWN
Requires-Dist: click
Requires-Dist: beautifulsoup4
Requires-Dist: httpx
Requires-Dist: pytz
Requires-Dist: sqlite-utils
Provides-Extra: test
Requires-Dist: pytest ; extra == 'test'
